02_Basic_Combinational/decoder_3x8/decoder_3x8.v
module decoder3x8_gatelevel(
    input [2:0] a,
    output y0, y1, y2, y3, y4, y5, y6, y7
);

wire a0_bar, a1_bar, a2_bar;

not (a0_bar, a[0]);
not (a1_bar, a[1]);
not (a2_bar, a[2]);

and (y0, a2_bar, a1_bar, a0_bar);
and (y1, a2_bar, a1_bar, a[0]);
and (y2, a2_bar, a[1], a0_bar);
and (y3, a2_bar, a[1], a[0]);
and (y4, a[2], a1_bar, a0_bar);
and (y5, a[2], a1_bar, a[0]);
and (y6, a[2], a[1], a0_bar);
and (y7, a[2], a[1], a[0]);

endmodule

02_Basic_Combinational/decoder_3x8/decoder_3x8_tb.v

module decoder3x8_tb;

reg [2:0] a;
wire y0, y1, y2, y3, y4, y5, y6, y7;

decoder3x8_gatelevel uut(
    .a(a),
    .y0(y0),
    .y1(y1),
    .y2(y2),
    .y3(y3),
    .y4(y4),
    .y5(y5),
    .y6(y6),
    .y7(y7)
);

initial begin
    $dumpfile("wave.vcd");
    $dumpvars(0, decoder3x8_tb);

    $monitor("Time=%0t a=%b y0=%b y1=%b y2=%b y3=%b y4=%b y5=%b y6=%b y7=%b",
             $time, a, y0, y1, y2, y3, y4, y5, y6, y7);

    a = 3'b000; #5;
    a = 3'b001; #5;
    a = 3'b010; #5;
    a = 3'b011; #5;
    a = 3'b100; #5;
    a = 3'b101; #5;
    a = 3'b110; #5;
    a = 3'b111; #5;

    $finish;
end

endmodule

02_Basic_Combinational/decoder_3x8/wave.vcd
$date
	Wed Jul  1 09:37:43 2026
$end
$version
	Icarus Verilog
$end
$timescale
	1s
$end
$scope module decoder3x8_tb $end
$var wire 1 ! y7 $end
$var wire 1 " y6 $end
$var wire 1 # y5 $end
$var wire 1 $ y4 $end
$var wire 1 % y3 $end
$var wire 1 & y2 $end
$var wire 1 ' y1 $end
$var wire 1 ( y0 $end
$var reg 3 ) a [2:0] $end
$scope module uut $end
$var wire 3 * a [2:0] $end
$var wire 1 + a0_bar $end
$var wire 1 , a1_bar $end
$var wire 1 - a2_bar $end
$var wire 1 ( y0 $end
$var wire 1 ' y1 $end
$var wire 1 & y2 $end
$var wire 1 % y3 $end
$var wire 1 $ y4 $end
$var wire 1 # y5 $end
$var wire 1 " y6 $end
$var wire 1 ! y7 $end
$upscope $end
$upscope $end
$enddefinitions $end
$comment Show the parameter values. $end
$dumpall
$end
#0
$dumpvars
1-
1,
1+
b0 *
b0 )
1(
0'
0&
0%
0$
0#
0"
0!
$end
#5
0(
0+
1'
b1 )
b1 *
#10
1&
1+
0,
0'
b10 )
b10 *
#15
0&
0+
1%
b11 )
b11 *
#20
1$
1+
1,
0-
0%
b100 )
b100 *
#25
0$
0+
1#
b101 )
b101 *
#30
1"
1+
0,
0#
b110 )
b110 *
#35
0"
0+
1!
b111 )
b111 *
