02_Basic_Combinational/demux_1x4/demux_1x4.v
//y0 = s1's0'i
//y1 = s1's0i
//y2y3..
module demux1x4_gatelevel(
    input i,
    input [1:0] sel,
    output y0, y1, y2, y3
);

wire s0_bar, s1_bar;

not (s0_bar, sel[0]);
not (s1_bar, sel[1]);

and (y0, i, s1_bar, s0_bar);
and (y1, i, s1_bar, sel[0]);
and (y2, i, sel[1], s0_bar);
and (y3, i, sel[1], sel[0]);

endmodule

02_Basic_Combinational/demux_1x4/demux_1x4_tb.v

module demux1x4_tb;

reg i;
reg [1:0] sel;
wire y0, y1, y2, y3;

demux1x4_gatelevel uut(
    .i(i),
    .sel(sel),
    .y0(y0),
    .y1(y1),
    .y2(y2),
    .y3(y3)
);

initial begin
    $dumpfile("wave.vcd");
    $dumpvars(0, demux1x4_tb);

    $monitor("Time=%0t i=%b sel=%b y0=%b y1=%b y2=%b y3=%b",
             $time, i, sel, y0, y1, y2, y3);

    i = 1;

    sel = 2'b00; #5;
    sel = 2'b01; #5;
    sel = 2'b10; #5;
    sel = 2'b11; #5;

    i = 0;

    sel = 2'b00; #5;
    sel = 2'b01; #5;
    sel = 2'b10; #5;
    sel = 2'b11; #5;

    $finish;
end

endmodule

02_Basic_Combinational/demux_1x4/wave.vcd
$date
	Wed Jul  1 08:40:55 2026
$end
$version
	Icarus Verilog
$end
$timescale
	1s
$end
$scope module demux1x4_tb $end
$var wire 1 ! y3 $end
$var wire 1 " y2 $end
$var wire 1 # y1 $end
$var wire 1 $ y0 $end
$var reg 1 % i $end
$var reg 2 & sel [1:0] $end
$scope module uut $end
$var wire 1 % i $end
$var wire 1 ' s0_bar $end
$var wire 1 ( s1_bar $end
$var wire 2 ) sel [1:0] $end
$var wire 1 $ y0 $end
$var wire 1 # y1 $end
$var wire 1 " y2 $end
$var wire 1 ! y3 $end
$upscope $end
$upscope $end
$enddefinitions $end
$comment Show the parameter values. $end
$dumpall
$end
#0
$dumpvars
b0 )
1(
1'
b0 &
1%
1$
0#
0"
0!
$end
#5
0$
0'
1#
b1 &
b1 )
#10
1"
1'
0(
0#
b10 &
b10 )
#15
0"
0'
1!
b11 &
b11 )
#20
1'
1(
0!
b0 &
b0 )
0%
#25
0'
b1 &
b1 )
#30
1'
0(
b10 &
b10 )
#35
0'
b11 &
b11 )
