02_Basic_Combinational/mux_4x1/mux_4x1.v

module mux4x1(
    input i0, i1, i2, i3,
    input [1:0] sel,
    output y
);

assign y = (sel == 2'b00) ? i0 :
           (sel == 2'b01) ? i1 :
           (sel == 2'b10) ? i2 : i3;

endmodule

02_Basic_Combinational/mux_4x1/mux_4x1_tb.v

module mux4x1_tb;

reg i0, i1, i2, i3;
reg [1:0] sel;
wire y;

mux4x1 uut(
    .i0(i0),
    .i1(i1),
    .i2(i2),
    .i3(i3),
    .sel(sel),
    .y(y)
);

initial begin
    $dumpfile("wave.vcd");
    $dumpvars(0, mux4x1_tb);

    $monitor("Time=%0t i0=%b i1=%b i2=%b i3=%b sel=%b y=%b",
             $time, i0, i1, i2, i3, sel, y);

    i0=0; i1=1; i2=0; i3=1;

    sel=2'b00; #5;
    sel=2'b01; #5;
    sel=2'b10; #5;
    sel=2'b11; #5;

    i0=1; i1=0; i2=1; i3=0;

    sel=2'b00; #5;
    sel=2'b01; #5;
    sel=2'b10; #5;
    sel=2'b11; #5;

    $finish;
end

endmodule

02_Basic_Combinational/mux_4x1/wave.vcd
$date
	Wed Jul  1 06:16:11 2026
$end
$version
	Icarus Verilog
$end
$timescale
	1s
$end
$scope module mux4x1_tb $end
$var wire 1 ! y $end
$var reg 1 " i0 $end
$var reg 1 # i1 $end
$var reg 1 $ i2 $end
$var reg 1 % i3 $end
$var reg 2 & sel [1:0] $end
$scope module uut $end
$var wire 1 " i0 $end
$var wire 1 # i1 $end
$var wire 1 $ i2 $end
$var wire 1 % i3 $end
$var wire 2 ' sel [1:0] $end
$var wire 1 ! y $end
$upscope $end
$upscope $end
$enddefinitions $end
$comment Show the parameter values. $end
$dumpall
$end
#0
$dumpvars
b0 '
b0 &
1%
0$
1#
0"
0!
$end
#5
1!
b1 &
b1 '
#10
0!
b10 &
b10 '
#15
1!
b11 &
b11 '
#20
b0 &
b0 '
0%
1$
0#
1"
#25
0!
b1 &
b1 '
#30
1!
b10 &
b10 '
#35
0!
b11 &
b11 '
