02_Basic_Combinational/Mux_2x1/mux_2x1.v
module mux2x1(
    input a, b, sel,
    output reg y
);

always @(*) begin
    if (sel)
        y = b;
    else
        y = a;
end

endmodule

02_Basic_Combinational/Mux_2x1/mux_2x1_tb.v
module mux2x1_tb;

reg a, b, sel;
wire y;

mux2x1 uut (
    .a(a),
    .b(b),
    .sel(sel),
    .y(y)
);

initial begin
    $dumpfile("wave.vcd");
    $dumpvars(0, mux2x1_tb);

    $monitor("Time=%0t a=%b b=%b sel=%b y=%b",
             $time, a, b, sel, y);

    a=0; b=0; sel=0; #5;
    a=0; b=1; sel=0; #5;
    a=1; b=0; sel=0; #5;
    a=1; b=1; sel=0; #5;

    a=0; b=0; sel=1; #5;
    a=0; b=1; sel=1; #5;
    a=1; b=0; sel=1; #5;
    a=1; b=1; sel=1; #5;

    $finish;
end

endmodule

02_Basic_Combinational/Mux_2x1/wave.vcd
$date
	Wed Jul  1 05:52:49 2026
$end
$version
	Icarus Verilog
$end
$timescale
	1s
$end
$scope module mux2x1_tb $end
$var wire 1 ! y $end
$var reg 1 " a $end
$var reg 1 # b $end
$var reg 1 $ sel $end
$scope module uut $end
$var wire 1 " a $end
$var wire 1 # b $end
$var wire 1 $ sel $end
$var reg 1 ! y $end
$upscope $end
$upscope $end
$enddefinitions $end
$comment Show the parameter values. $end
$dumpall
$end
#0
$dumpvars
0$
0#
0"
0!
$end
#5
1#
#10
1!
0#
1"
#15
1#
#20
0!
1$
0#
0"
#25
1!
1#
#30
0!
0#
1"
#35
1!
1#
